{
    "upgradesForBuy": [
        {
            "id": "int_business_units",
            "name": "Business units",
            "price": 161.46,
            "profitPerHour": 2.014,
            "condition": null,
            "cooldownSeconds": 0,
            "section": "Specials",
            "level": 13,
            "currentProfitPerHour": 1.789,
            "profitPerHourDelta": 0.225,
            "isAvailable": true,
            "isExpired": false,
            "totalCooldownSeconds": 21600
        },
        {
            "id": "int_startup_acquisition",
            "name": "Startup acquisition",
            "price": 319.68,
            "profitPerHour": 2.255,
            "condition": null,
            "cooldownSeconds": 0,
            "section": "Specials",
            "level": 14,
            "currentProfitPerHour": 2.014,
            "profitPerHourDelta": 0.241,
            "isAvailable": true,
            "isExpired": false,
            "totalCooldownSeconds": 21600
        },
        {
            "id": "int_time_for_savings",
            "name": "Time for savings",
            "price": 159.84,
            "profitPerHour": 1.127,
            "condition": null,
            "cooldownSeconds": 0,
            "section": "Specials",
            "level": 14,
            "currentProfitPerHour": 1.007,
            "profitPerHourDelta": 0.12,
            "isAvailable": true,
            "isExpired": false,
            "totalCooldownSeconds": 21600
        },
        {
            "id": "int_dev_culture",
            "name": "Dev culture",
            "price": 332.3,
            "profitPerHour": 1.256,
            "condition": null,
            "cooldownSeconds": 0,
            "section": "Specials",
            "level": 15,
            "currentProfitPerHour": 1.1269999999999998,
            "profitPerHourDelta": 0.129,
            "isAvailable": true,
            "isExpired": false,
            "totalCooldownSeconds": 21600
        },
        {
            "id": "int_year_strategy",
            "name": "Year strategy",
            "price": 0,
            "profitPerHour": 0.358,
            "condition": null,
            "cooldownSeconds": 0,
            "section": "Specials",
            "maxLevel": 5,
            "level": 6,
            "currentProfitPerHour": 0.28800000000000003,
            "profitPerHourDelta": 0.07,
            "isAvailable": true,
            "isExpired": false,
            "totalCooldownSeconds": 21600
        },
        {
            "id": "adv_integration_1809",
            "name": "New hairstyle",
            "toggle": {
                "enableAt": "2024-09-21T09:00:00.000Z"
            },
            "expiresAt": "2024-09-24T09:00:00.000Z",
            "price": 8.56,
            "profitPerHour": 1.198,
            "condition": null,
            "cooldownSeconds": 0,
            "section": "Specials",
            "level": 9,
            "currentProfitPerHour": 1.026,
            "profitPerHourDelta": 0.172,
            "isAvailable": true,
            "isExpired": true,
            "totalCooldownSeconds": 21600
        },
        {
            "id": "int_hamster_racer",
            "name": "Hamster racer",
            "price": 16.73,
            "profitPerHour": 0.967,
            "condition": null,
            "cooldownSeconds": 8653,
            "section": "Specials",
            "level": 10,
            "currentProfitPerHour": 0.838,
            "profitPerHourDelta": 0.129,
            "isAvailable": true,
            "isExpired": false,
            "totalCooldownSeconds": 21600
        },
        {
            "id": "int_visiting_a_zoo",
            "name": "Visiting a zoo",
            "price": 28.61,
            "profitPerHour": 1.105,
            "condition": null,
            "cooldownSeconds": 8651,
            "section": "Specials",
            "level": 11,
            "currentProfitPerHour": 0.967,
            "profitPerHourDelta": 0.138,
            "isAvailable": true,
            "isExpired": false,
            "totalCooldownSeconds": 21600
        },
        {
            "id": "adv_integration_2409",
            "name": "Cycling in Amsterdam",
            "toggle": {
                "enableAt": "2024-09-24T09:00:00.000Z"
            },
            "expiresAt": "2024-09-26T09:00:00.000Z",
            "price": 1.28,
            "profitPerHour": 0.321,
            "condition": null,
            "cooldownSeconds": 0,
            "section": "Specials",
            "level": 3,
            "currentProfitPerHour": 0.20700000000000002,
            "profitPerHourDelta": 0.114,
            "isAvailable": true,
            "isExpired": true,
            "totalCooldownSeconds": 21600
        },
        {
            "id": "int_dyor",
            "name": "DYOR",
            "toggle": {
                "enableAt": "2024-09-28T11:00:00.000Z"
            },
            "price": 3.1,
            "profitPerHour": 0.444,
            "condition": null,
            "cooldownSeconds": 8639,
            "section": "Specials",
            "level": 4,
            "currentProfitPerHour": 0.321,
            "profitPerHourDelta": 0.123,
            "isAvailable": true,
            "isExpired": false,
            "totalCooldownSeconds": 21600
        },
        {
            "id": "int_amusement_park",
            "name": "Amusement park",
            "toggle": {
                "enableAt": "2024-09-29T11:00:00.000Z"
            },
            "price": 1.28,
            "profitPerHour": 0.321,
            "condition": null,
            "cooldownSeconds": 8637,
            "section": "Specials",
            "level": 3,
            "currentProfitPerHour": 0.20700000000000002,
            "profitPerHourDelta": 0.114,
            "isAvailable": true,
            "isExpired": false,
            "totalCooldownSeconds": 21600
        },
        {
            "id": "int_buying_an_apartment",
            "name": "Buying an apartment",
            "toggle": {
                "enableAt": "2024-09-30T11:00:00.000Z"
            },
            "price": 2.21,
            "profitPerHour": 0.207,
            "condition": null,
            "cooldownSeconds": 8632,
            "section": "Specials",
            "level": 2,
            "currentProfitPerHour": 0.1,
            "profitPerHourDelta": 0.107,
            "isAvailable": true,
            "isExpired": false,
            "totalCooldownSeconds": 21600
        },
        {
            "id": "int_shopping",
            "name": "Shopping",
            "toggle": {
                "enableAt": "2024-10-01T11:00:00.000Z"
            },
            "price": 2.21,
            "profitPerHour": 0.207,
            "condition": null,
            "cooldownSeconds": 8628,
            "section": "Specials",
            "level": 2,
            "currentProfitPerHour": 0.1,
            "profitPerHourDelta": 0.107,
            "isAvailable": true,
            "isExpired": false,
            "totalCooldownSeconds": 21600
        }
    ]
}